epftool/__init__.py
epftool/__main__.py
epftool/cli.py
epftool-1.0.0.dist-info/LICENSE
epftool-1.0.0.dist-info/METADATA
epftool-1.0.0.dist-info/WHEEL
epftool-1.0.0.dist-info/entry_points.txt
epftool-1.0.0.dist-info/top_level.txt
epftool-1.0.0.dist-info/RECORD
